<biblioteca>
    <cancion nombre="BOMMBAYAH">
        <artista>"BLACKPINK"</artista>
        <album>"IN YOUR AREA"</album>
        <imagen>"Reproductor/recursos/imagenes/inYourArea.jpeg"</imagen>
        <ruta>"recursos/musica/BLACKPINK - BOOMBAYAH.mp3"</ruta>
    </cancion>
    <cancion nombre="AS IF ITS YOUR LAST">
        <artista>"BLACKPINK"</artista>
        <album>"IN YOUR AREA"</album>
        <imagen>"recursos/imagenes/inYourArea.jpeg"</imagen>
        <ruta>"recursos/musica/BLACKPINK - AS IF ITS YOUR LAST.mp3"</ruta>
    </cancion>
    <cancion nombre="Come 2gether">
        <artista>"Ooyy"</artista>
        <album>"Epidemic Electronic"</album>
        <imagen>"recursos/imagenes/come2gether.jpeg"</imagen>
        <ruta>"recursos/musica/Ooyy Come 2gether.mp3"</ruta>
    </cancion>

    
</biblioteca>
